fastapi_restful_myfork/__init__.py
fastapi_restful_myfork/api_model.py
fastapi_restful_myfork/api_settings.py
fastapi_restful_myfork/camelcase.py
fastapi_restful_myfork/cbv.py
fastapi_restful_myfork/cbv_base.py
fastapi_restful_myfork/enums.py
fastapi_restful_myfork/guid_type.py
fastapi_restful_myfork/inferring_router.py
fastapi_restful_myfork/openapi.py
fastapi_restful_myfork/py.typed
fastapi_restful_myfork/session.py
fastapi_restful_myfork/tasks.py
fastapi_restful_myfork/timing.py
fastapi_restful_myfork-0.5.0.dist-info/LICENSE
fastapi_restful_myfork-0.5.0.dist-info/METADATA
fastapi_restful_myfork-0.5.0.dist-info/WHEEL
fastapi_restful_myfork-0.5.0.dist-info/RECORD
