Metadata-Version: 2.1
Name: fastapi-restful-myfork
Version: 0.5.0
Summary: Quicker FastApi developing tools
Home-page: https://fastapi-restful.netlify.app
License: MIT
Keywords: fastapi,OOP,RESTful
Author: Yuval Levi
Author-email: yuvall9313@gmail.com
Requires-Python: >=3.7,<4.0
Classifier: Development Status :: 4 - Beta
Classifier: Environment :: Web Environment
Classifier: Framework :: AsyncIO
Classifier: Framework :: FastAPI
Classifier: Intended Audience :: Developers
Classifier: Intended Audience :: Information Technology
Classifier: Intended Audience :: System Administrators
Classifier: License :: OSI Approved :: MIT License
Classifier: Operating System :: OS Independent
Classifier: Programming Language :: Python
Classifier: Programming Language :: Python :: 3
Classifier: Programming Language :: Python :: 3.7
Classifier: Programming Language :: Python :: 3.8
Classifier: Programming Language :: Python :: 3.9
Classifier: Programming Language :: Python :: 3.10
Classifier: Programming Language :: Python :: 3.11
Classifier: Programming Language :: Python :: 3.12
Classifier: Programming Language :: Python :: 3 :: Only
Classifier: Topic :: Internet
Classifier: Topic :: Internet :: WWW/HTTP
Classifier: Topic :: Internet :: WWW/HTTP :: HTTP Servers
Classifier: Topic :: Software Development
Classifier: Topic :: Software Development :: Libraries
Classifier: Topic :: Software Development :: Libraries :: Python Modules
Classifier: Topic :: Utilities
Classifier: Typing :: Typed
Provides-Extra: all
Provides-Extra: session
Requires-Dist: fastapi (>=0.89,<1.0)
Requires-Dist: psutil (>=5,<6)
Requires-Dist: pydantic (>1.0,<3.0)
Requires-Dist: pydantic-settings (>=2.0.1,<3.0.0) ; extra == "all"
Requires-Dist: sqlalchemy (>=1.4,<3.0) ; extra == "all" or extra == "session"
Requires-Dist: typing-inspect (>=0.9.0,<0.10.0) ; extra == "all"
Project-URL: Documentation, https://fastapi-restful.netlify.app
Project-URL: Repository, https://github.com/yuval9313/FastApi-RESTful
